README.md
consolemsg.py
setup.py
consolemsg.egg-info/PKG-INFO
consolemsg.egg-info/SOURCES.txt
consolemsg.egg-info/dependency_links.txt
consolemsg.egg-info/top_level.txt